lepsius/__init__.py
lepsius/carbon.py
Lepsius-0.0.1.dist-info/DESCRIPTION.rst
Lepsius-0.0.1.dist-info/METADATA
Lepsius-0.0.1.dist-info/metadata.json
Lepsius-0.0.1.dist-info/RECORD
Lepsius-0.0.1.dist-info/top_level.txt
Lepsius-0.0.1.dist-info/WHEEL
Lepsius-0.0.1.dist-info/zip-safe
