Metadata-Version: 2.0
Name: Lepsius
Version: 0.0.1
Summary: Reads live log.
Home-page: https://github.com/bearstech/lepsius
Author: Mathieu Lecarme
Author-email: mathieu@garambrogne.net
License: BSD
Platform: UNKNOWN
Classifier: Development Status :: 3 - Alpha
Classifier: Environment :: Console
Classifier: Intended Audience :: Developers
Classifier: Operating System :: POSIX
Classifier: Operating System :: MacOS :: MacOS X
Classifier: Programming Language :: Python
Classifier: Natural Language :: French
Requires-Dist: regex
Requires-Dist: pygrok
Requires-Dist: pygtail
